odoo/addons/product_supplierinfo_for_customer_invoice/README.rst
odoo/addons/product_supplierinfo_for_customer_invoice/__init__.py
odoo/addons/product_supplierinfo_for_customer_invoice/__manifest__.py
odoo/addons/product_supplierinfo_for_customer_invoice/i18n/de.po
odoo/addons/product_supplierinfo_for_customer_invoice/i18n/es.po
odoo/addons/product_supplierinfo_for_customer_invoice/i18n/it.po
odoo/addons/product_supplierinfo_for_customer_invoice/i18n/product_supplierinfo_for_customer_invoice.pot
odoo/addons/product_supplierinfo_for_customer_invoice/i18n/pt.po
odoo/addons/product_supplierinfo_for_customer_invoice/i18n/pt_BR.po
odoo/addons/product_supplierinfo_for_customer_invoice/models/__init__.py
odoo/addons/product_supplierinfo_for_customer_invoice/models/account_invoice.py
odoo/addons/product_supplierinfo_for_customer_invoice/readme/CONTRIBUTORS.rst
odoo/addons/product_supplierinfo_for_customer_invoice/readme/DESCRIPTION.rst
odoo/addons/product_supplierinfo_for_customer_invoice/static/description/icon.png
odoo/addons/product_supplierinfo_for_customer_invoice/static/description/index.html
odoo/addons/product_supplierinfo_for_customer_invoice/views/account_invoice_view.xml
odoo12_addon_product_supplierinfo_for_customer_invoice-12.0.1.0.0.99.dev13.dist-info/METADATA
odoo12_addon_product_supplierinfo_for_customer_invoice-12.0.1.0.0.99.dev13.dist-info/WHEEL
odoo12_addon_product_supplierinfo_for_customer_invoice-12.0.1.0.0.99.dev13.dist-info/top_level.txt
odoo12_addon_product_supplierinfo_for_customer_invoice-12.0.1.0.0.99.dev13.dist-info/RECORD
